ponddy_api_test_client/__init__.py
ponddy_api_test_client-0.0.1.dist-info/METADATA
ponddy_api_test_client-0.0.1.dist-info/WHEEL
ponddy_api_test_client-0.0.1.dist-info/top_level.txt
ponddy_api_test_client-0.0.1.dist-info/RECORD
